vdbfusion-0.1.6.dist-info/METADATA
vdbfusion-0.1.6.dist-info/RECORD
vdbfusion-0.1.6.dist-info/LICENSE.txt
vdbfusion-0.1.6.dist-info/WHEEL
vdbfusion-0.1.6.dist-info/top_level.txt
vdbfusion/__init__.py
vdbfusion/pybind/vdbfusion_pybind.cpython-38-x86_64-linux-gnu.so
vdbfusion/pybind/vdb_volume.py
vdbfusion/pybind/__init__.py
