Metadata-Version: 2.1
Name: vdbfusion
Version: 0.1.6
Summary: 3D Volumetric Surface Reconstruction using the VDB data structure
Home-page: UNKNOWN
Author: Ignacio Martin Vizzo (aka Nacho) and Cyrill Stachniss
Author-email: ignaciovizzo@gmail.com
License: UNKNOWN
Keywords: TSDF,Mapping,SLAM,LiDAR,Odometry,Localization
Platform: UNKNOWN
Classifier: License :: OSI Approved :: MIT License
Classifier: Operating System :: Unix
Classifier: Programming Language :: Python
Classifier: Programming Language :: Python :: 2.7
Classifier: Programming Language :: Python :: 3.3
Classifier: Programming Language :: Python :: 3.4
Classifier: Programming Language :: Python :: 3.5
Classifier: Programming Language :: Python :: 3.6
Classifier: Programming Language :: Python :: 3.7
Classifier: Programming Language :: Python :: 3.8
License-File: LICENSE.txt
Requires-Dist: numpy
Provides-Extra: test
Requires-Dist: pytest ; extra == 'test'
